pachisi_render/__init__.py
pachisi_render/main.py
pachisi_render/api/__init__.py
pachisi_render/api/api.py
pachisi_render/api/board_adapter.py
pachisi_render/api/colorscheme.py
pachisi_render/api/state.py
pachisi_render/renderer/__init__.py
pachisi_render/renderer/board.py
pachisi_render/renderer/layout.py
pachisi_render/renderer/renderer.py
pachisi_render-0.0.1.dist-info/LICENSE
pachisi_render-0.0.1.dist-info/METADATA
pachisi_render-0.0.1.dist-info/WHEEL
pachisi_render-0.0.1.dist-info/entry_points.txt
pachisi_render-0.0.1.dist-info/top_level.txt
pachisi_render-0.0.1.dist-info/RECORD
