Metadata-Version: 2.1
Name: pachisi-render
Version: 0.0.1
Summary: Flexible rendering of pachisi boards
Author-email: Jakob Gretenkort <jakob.gretenkort@student.kit.edu>, Michael König <m.koenig@kit.edu>, Hendrik Mahrt <hendrik.mahrt@kit.edu>
Maintainer-email: Jakob Gretenkort <jakob.gretenkort@student.kit.edu>
Keywords: game,REST
Classifier: Development Status :: 4 - Beta
Classifier: Programming Language :: Python
Classifier: Programming Language :: Python :: 3.11
Classifier: Programming Language :: Python :: 3.10
Classifier: Programming Language :: Python :: 3.9
Classifier: Programming Language :: Python :: 3.8
Classifier: Intended Audience :: Education
Classifier: License :: OSI Approved :: MIT License
Classifier: Topic :: Games/Entertainment :: Board Games
Requires-Python: >=3.8
License-File: LICENSE
Requires-Dist: drawsvg[all]
Requires-Dist: pydantic
Requires-Dist: fastapi
Requires-Dist: uvicorn
Provides-Extra: lint
Requires-Dist: black ; extra == 'lint'
Requires-Dist: isort ; extra == 'lint'
Requires-Dist: pylint ; extra == 'lint'
Requires-Dist: mypy ; extra == 'lint'
Provides-Extra: test
Requires-Dist: pytest ; extra == 'test'
Requires-Dist: requests ; extra == 'test'
